autosar/__init__.py
autosar/_swc_implementation.py
autosar/base.py
autosar/behavior.py
autosar/builder.py
autosar/component.py
autosar/constant.py
autosar/datatype.py
autosar/element.py
autosar/mode.py
autosar/package.py
autosar/port.py
autosar/portinterface.py
autosar/signal.py
autosar/system.py
autosar/workspace.py
autosar/bsw/__init__.py
autosar/bsw/com.py
autosar/bsw/generator.py
autosar/bsw/os.py
autosar/parser/__init__.py
autosar/parser/behavior_parser.py
autosar/parser/component_parser.py
autosar/parser/constant_parser.py
autosar/parser/datatype_parser.py
autosar/parser/mode_parser.py
autosar/parser/package_parser.py
autosar/parser/parser_base.py
autosar/parser/portinterface_parser.py
autosar/parser/signal_parser.py
autosar/parser/swc_implementation_parser.py
autosar/parser/system_parser.py
autosar/rte/__init__.py
autosar/rte/base.py
autosar/rte/config.py
autosar/rte/generator.py
autosar/rte/partition.py
autosar/util/__init__.py
autosar/util/dcf.py
autosar/writer/__init__.py
autosar/writer/behavior_writer.py
autosar/writer/component_writer.py
autosar/writer/constant_writer.py
autosar/writer/datatype_writer.py
autosar/writer/mode_writer.py
autosar/writer/package_writer.py
autosar/writer/portinterface_writer.py
autosar/writer/signal_writer.py
autosar/writer/workspace_writer.py
autosar/writer/writer_base.py
autosar-0.4.2.dist-info/LICENSE
autosar-0.4.2.dist-info/METADATA
autosar-0.4.2.dist-info/WHEEL
autosar-0.4.2.dist-info/top_level.txt
autosar-0.4.2.dist-info/RECORD
