Metadata-Version: 2.1
Name: autosar
Version: 0.4.2
Summary: A set of Python modules for working with AUTOSAR XML files
Home-page: http://github.com/cogu/autosar
Author: Conny Gustafsson
Author-email: congus8@gmail.com
License: MIT
Project-URL: Documentation, https://autosar.readthedocs.io/
Classifier: Development Status :: 3 - Alpha
Classifier: License :: OSI Approved :: MIT License
Classifier: Programming Language :: Python :: 3.4
Classifier: Topic :: Text Processing :: Markup :: XML
License-File: LICENSE
Requires-Dist: cfile ==0.2.0
